sinapsis/__init__.py
sinapsis/bin/sinapsis_cli.py
sinapsis/configs/hello_world_agent.yml
sinapsis/templates/__init__.py
sinapsis/templates/display_hello_world.py
sinapsis/templates/hello_world.py
sinapsis/webapp/__init__.py
sinapsis/webapp/agent_gradio_helper.py
sinapsis/webapp/agent_webapp_utils.py
sinapsis/webapp/chatbot_base.py
sinapsis/webapp/tts_base.py
sinapsis-0.2.25.dist-info/licenses/LICENSE
sinapsis-0.2.25.dist-info/METADATA
sinapsis-0.2.25.dist-info/WHEEL
sinapsis-0.2.25.dist-info/entry_points.txt
sinapsis-0.2.25.dist-info/top_level.txt
sinapsis-0.2.25.dist-info/RECORD
