Metadata-Version: 2.4
Name: sinapsis
Version: 0.2.25
Summary: Modular and Universal AI platform
Author-email: SinapsisAI <dev@sinapsis.tech>
Project-URL: Homepage, https://sinapsis.tech
Project-URL: Documentation, https://docs.sinapsis.tech/docs
Project-URL: Tutorials, https://docs.sinapsis.tech/tutorials
Project-URL: Repository, https://github.com/Sinapsis-AI/sinapsis.git
Requires-Python: >=3.10
License-File: LICENSE
Requires-Dist: sinapsis-core>=0.2.2
Provides-Extra: all
Requires-Dist: sinapsis[dev]; extra == "all"
Provides-Extra: webapp
Requires-Dist: gradio<=5.23; extra == "webapp"
Dynamic: license-file
